LICENSE
MANIFEST.in
README
setup.py
esr/__init__.py
esr/esr.py
esr/records.py
esr/utils/__init__.py
esr/utils/utils.py
python_esr.egg-info/PKG-INFO
python_esr.egg-info/SOURCES.txt
python_esr.egg-info/dependency_links.txt
python_esr.egg-info/not-zip-safe
python_esr.egg-info/top_level.txt
tests/__init__.py
tests/test_esr.py
tests/data/esr_type3.v11
tests/data/esr_type4.v11