Metadata-Version: 1.0
Name: python-esr
Version: 0.2
Summary: Swiss ESR account statement record parser
Home-page: https://bitbucket.org/loss/python-esr
Author: Leuchter Open Source Solutions AG
Author-email: tryton@leuchterag.ch
License: GPL-3
Platform: UNKNOWN
Classifier: Development Status :: 5 - Production/Stable
Classifier: Intended Audience :: Developers
Classifier: Intended Audience :: Financial and Insurance Industry
Classifier: License :: OSI Approved :: GNU General Public License v3 (GPLv3)
Classifier: Operating System :: OS Independent
Classifier: Programming Language :: Python :: 2
Classifier: Programming Language :: Python :: 3
Classifier: Topic :: Office/Business :: Financial
Classifier: Topic :: Office/Business :: Financial :: Accounting
Classifier: Topic :: Software Development :: Libraries :: Python Modules
